LICENSE
MANIFEST.in
README.md
pyproject.toml
setup.py
dank/DankEncoder.py
dank/DankGenerator.py
dank/__init__.py
dank.egg-info/PKG-INFO
dank.egg-info/SOURCES.txt
dank.egg-info/dependency_links.txt
dank.egg-info/not-zip-safe
dank.egg-info/requires.txt
dank.egg-info/top_level.txt
dank/_dank/dank.cpp
dank/_dank/dfa.cpp
dank/_dank/encoder.cpp
dank/_dank/nfa.cpp
dank/_dank/include/dfa.h
dank/_dank/include/encoder.h
dank/_dank/include/infint.h
dank/_dank/include/nfa.h